{
  "id": "gallery",
  "type": "SharedSlice",
  "name": "Gallery",
  "description": "Gallery",
  "variations": [
    {
      "id": "default",
      "name": "Default",
      "docURL": "...",
      "version": "initial",
      "description": "Default",
      "imageUrl": "",
      "primary": {
        "galleryItem": {
          "type": "Group",
          "config": {
            "label": "Gallery Item",
            "repeat": true,
            "fields": {
              "title": {
                "type": "Text",
                "config": {
                  "label": "Title",
                  "placeholder": ""
                }
              },
              "text": {
                "type": "Text",
                "config": {
                  "label": "Text",
                  "placeholder": ""
                }
              },
              "image": {
                "type": "Image",
                "config": {
                  "label": "Image",
                  "constraint": {},
                  "thumbnails": []
                }
              },
              "link": {
                "type": "Link",
                "config": {
                  "label": "Link",
                  "placeholder": "",
                  "select": null,
                  "allowTargetBlank": false,
                  "allowText": true,
                  "repeat": false
                }
              }
            }
          }
        },
        "link": {
          "type": "Link",
          "config": {
            "label": "Link",
            "placeholder": "",
            "select": null,
            "allowTargetBlank": true,
            "allowText": true,
            "repeat": false
          }
        }
      },
      "items": {}
    }
  ]
}